snek5000_tgv/Snakefile
snek5000_tgv/__init__.py
snek5000_tgv/output.py
snek5000_tgv/solver.py
snek5000_tgv/tgv.par.cfg
snek5000_tgv/tgv.usr.f
snek5000_tgv-0.2.0.dist-info/LICENSE
snek5000_tgv-0.2.0.dist-info/METADATA
snek5000_tgv-0.2.0.dist-info/WHEEL
snek5000_tgv-0.2.0.dist-info/entry_points.txt
snek5000_tgv-0.2.0.dist-info/top_level.txt
snek5000_tgv-0.2.0.dist-info/RECORD
