Metadata-Version: 2.1
Name: snek5000-tgv
Version: 0.2.0
Summary: Taylor-Green vortex
License: ...
License-File: LICENSE
Requires-Dist: snek5000 (>=0.9.0rc3)
